{
  "project_info": {
    "project_number": "625036011515",
    "project_id": "haleyora-course",
    "storage_bucket": "haleyora-course.appspot.com"
  },
  "client": [
    {
      "client_info": {
        "mobilesdk_app_id": "1:625036011515:android:dbb169fa4b7b6bdec1cd5e",
        "android_client_info": {
          "package_name": "com.haleyora.course"
        }
      },
      "oauth_client": [],
      "api_key": [
        {
          "current_key": "AIzaSyB6Vv2a826VwS_LAUZnTZyOLRSKg8HEi34"
        }
      ],
      "services": {
        "appinvite_service": {
          "other_platform_oauth_client": []
        }
      }
    }
  ],
  "configuration_version": "1"
}